<annotation>
	<folder>dataset-platnomor</folder>
	<filename>Cars4.png</filename>
	<path>D:\Project\PYTHON\labelimg\dataset-platnomor\Cars4.png</path>
	<source>
		<database>Unknown</database>
	</source>
	<size>
		<width>590</width>
		<height>350</height>
		<depth>3</depth>
	</size>
	<segmented>0</segmented>
	<object>
		<name>plat nomor</name>
		<pose>Unspecified</pose>
		<truncated>0</truncated>
		<difficult>0</difficult>
		<bndbox>
			<xmin>82</xmin>
			<ymin>57</ymin>
			<xmax>545</xmax>
			<ymax>248</ymax>
		</bndbox>
	</object>
</annotation>
